Workbook

Sheet Budget
A1: GreenLeaf Trading Pte Ltd — FY2026 Budget (S$)
A3: Account | B3: Jan | C3: Feb | D3: Mar | E3: Apr | F3: May | G3: Jun | H3: Jul | I3: Aug | J3: Sep | K3: Oct | L3: Nov | M3: Dec | N3: Total
A4: Sales | B4: 90000 | C4: 91800 | D4: 93636 | E4: 95509 | F4: 97419 | G4: 99367 | H4: 101354 | I4: 103381 | J4: 105449 | K4: 107558 | L4: 109709 | M4: 111903 | N4: =SUM(B4:M4) -> 1207085
A5: Sales Commission | B5: 4500 | C5: 4590 | D5: 4682 | E5: 4776 | F5: 4872 | G5: 4969 | H5: 5068 | I5: 5169 | J5: 5272 | K5: 5377 | L5: 5485 | M5: 5595 | N5: =SUM(B5:M5) -> 60355
A6: Direct Costs | B6: 49500 | C6: 50490 | D6: 51500 | E6: 52530 | F6: 53581 | G6: 54653 | H6: 55746 | I6: 56861 | J6: 57998 | K6: 59158 | L6: 60341 | M6: 61548 | N6: =SUM(B6:M6) -> 663906
A7: Office Rent | B7: 8000 | C7: 8000 | D7: 8000 | E7: 8000 | F7: 8000 | G7: 8000 | H7: 8000 | I7: 8000 | J7: 8000 | K7: 8000 | L7: 8000 | M7: 8000 | N7: =SUM(B7:M7) -> 96000
A8: Salaries | B8: 17500 | C8: 17500 | D8: 17500 | E8: 17500 | F8: 17500 | G8: 17500 | H8: 17500 | I8: 17500 | J8: 17500 | K8: 17500 | L8: 17500 | M8: 17500 | N8: =SUM(B8:M8) -> 210000
A9: Marketing | B9: 4000 | C9: 4000 | D9: 4000 | E9: 4000 | F9: 4000 | G9: 4000 | H9: 4000 | I9: 4000 | J9: 4000 | K9: 4000 | L9: 4000 | M9: 4000 | N9: =SUM(B9:M9) -> 48000
A10: Utilities | B10: 1500 | C10: 1500 | D10: 1500 | E10: 1500 | F10: 1500 | G10: 1500 | H10: 1500 | I10: 1500 | J10: 1500 | K10: 1500 | L10: 1500 | M10: 1500 | N10: =SUM(B10:M10) -> 18000
A11: Other Expenses | B11: 1800 | C11: 1800 | D11: 1800 | E11: 1800 | F11: 1800 | G11: 1800 | H11: 1800 | I11: 1800 | J11: 1800 | K11: 1800 | L11: 1800 | M11: 1800 | N11: =SUM(B11:M11) -> 21600

Sheet Actual
A1: GreenLeaf Trading Pte Ltd — FY2026 Actual (S$)
A3: Account | B3: Jan | C3: Feb | D3: Mar | E3: Apr | F3: May | G3: Jun | H3: Jul | I3: Aug | J3: Sep | K3: Oct | L3: Nov | M3: Dec | N3: Total
A4: Sales | B4: 87300 | C4: 89046 | D4: 90827 | E4: 92644 | F4: 94496 | G4: 96386 | H4: 98313 | I4: 100280 | J4: 102286 | K4: 104331 | L4: 106418 | M4: 108546 | N4: =SUM(B4:M4) -> 1170873
A5: Sales Commission | B5: 4365 | C5: 4452 | D5: 4542 | E5: 4633 | F5: 4726 | G5: 4820 | H5: 4916 | I5: 5014 | J5: 5114 | K5: 5216 | L5: 5320 | M5: 5427 | N5: =SUM(B5:M5) -> 58545
A6: Direct Costs | B6: 51480 | C6: 52510 | D6: 53560 | E6: 54631 | F6: 55724 | G6: 56839 | H6: 57976 | I6: 59135 | J6: 60318 | K6: 61524 | L6: 62755 | M6: 64010 | N6: =SUM(B6:M6) -> 690462
A7: Office Rent | B7: 8000 | C7: 8000 | D7: 8000 | E7: 8000 | F7: 8000 | G7: 8000 | H7: 8000 | I7: 8000 | J7: 8000 | K7: 8000 | L7: 8000 | M7: 8000 | N7: =SUM(B7:M7) -> 96000
A8: Salaries | B8: 17850 | C8: 17850 | D8: 17850 | E8: 17850 | F8: 17850 | G8: 17850 | H8: 17850 | I8: 17850 | J8: 17850 | K8: 17850 | L8: 17850 | M8: 17850 | N8: =SUM(B8:M8) -> 214200
A9: Marketing | B9: 5120 | C9: 5120 | D9: 5120 | E9: 5120 | F9: 5120 | G9: 5120 | H9: 5120 | I9: 5120 | J9: 5120 | K9: 5120 | L9: 5120 | M9: 5120 | N9: =SUM(B9:M9) -> 61440
A10: Utilities | B10: 1605 | C10: 1605 | D10: 1605 | E10: 1605 | F10: 1605 | G10: 1605 | H10: 1605 | I10: 1605 | J10: 1605 | K10: 1605 | L10: 1605 | M10: 1605 | N10: =SUM(B10:M10) -> 19260
A11: Other Expenses | B11: 1656 | C11: 1656 | D11: 1656 | E11: 1656 | F11: 1656 | G11: 1656 | H11: 1656 | I11: 1656 | J11: 1656 | K11: 1656 | L11: 1656 | M11: 1656 | N11: =SUM(B11:M11) -> 19872

Sheet Variance
A1: Variance Analysis — Actual vs Budget (full year)
A2: Threshold: | B2: 0.1
A4: Account | B4: Type | C4: Budget | D4: Actual | E4: Variance | F4: Var % | G4: Classification
A5: Sales | B5: income | C5: =Budget!N4 -> 1207085 | D5: =Actual!N4 -> 1170873 | E5: =D5-C5 -> -36212 | F5: =E5/C5 -> -0.029999544 | G5: =IF(B5="income",IF(E5>=0,"Favourable","Adverse"),IF(E5<=0,"Favourable","Adverse")) -> Adverse
A6: Sales Commission | B6: expense | C6: =Budget!N5 -> 60355 | D6: =Actual!N5 -> 58545 | E6: =D6-C6 -> -1810 | F6: =E6/C6 -> -0.02998923 | G6: =IF(B6="income",IF(E6>=0,"Favourable","Adverse"),IF(E6<=0,"Favourable","Adverse")) -> Favourable
A7: Direct Costs | B7: expense | C7: =Budget!N6 -> 663906 | D7: =Actual!N6 -> 690462 | E7: =D7-C7 -> 26556 | F7: =E7/C7 -> 0.039999639 | G7: =IF(B7="income",IF(E7>=0,"Favourable","Adverse"),IF(E7<=0,"Favourable","Adverse")) -> Adverse
A8: Office Rent | B8: expense | C8: =Budget!N7 -> 96000 | D8: =Actual!N7 -> 96000 | E8: =D8-C8 -> 0 | F8: =E8/C8 -> 0 | G8: =IF(B8="income",IF(E8>=0,"Favourable","Adverse"),IF(E8<=0,"Favourable","Adverse")) -> Favourable
A9: Salaries | B9: expense | C9: =Budget!N8 -> 210000 | D9: =Actual!N8 -> 214200 | E9: =D9-C9 -> 4200 | F9: =E9/C9 -> 0.02 | G9: =IF(B9="income",IF(E9>=0,"Favourable","Adverse"),IF(E9<=0,"Favourable","Adverse")) -> Adverse
A10: Marketing | B10: expense | C10: =Budget!N9 -> 48000 | D10: =Actual!N9 -> 61440 | E10: =D10-C10 -> 13440 | F10: =E10/C10 -> 0.28 | G10: =IF(B10="income",IF(E10>=0,"Favourable","Adverse"),IF(E10<=0,"Favourable","Adverse")) -> Adverse
A11: Utilities | B11: expense | C11: =Budget!N10 -> 18000 | D11: =Actual!N10 -> 19260 | E11: =D11-C11 -> 1260 | F11: =E11/C11 -> 0.07 | G11: =IF(B11="income",IF(E11>=0,"Favourable","Adverse"),IF(E11<=0,"Favourable","Adverse")) -> Adverse
A12: Other Expenses | B12: expense | C12: =Budget!N11 -> 21600 | D12: =Actual!N11 -> 19872 | E12: =D12-C12 -> -1728 | F12: =E12/C12 -> -0.08 | G12: =IF(B12="income",IF(E12>=0,"Favourable","Adverse"),IF(E12<=0,"Favourable","Adverse")) -> Favourable
